docxblocks/__init__.py
docxblocks/constants.py
docxblocks/builders/bullet.py
docxblocks/builders/header_footer.py
docxblocks/builders/heading.py
docxblocks/builders/image.py
docxblocks/builders/page_break.py
docxblocks/builders/rich_text.py
docxblocks/builders/table.py
docxblocks/builders/text.py
docxblocks/core/inserter.py
docxblocks/schema/__init__.py
docxblocks/schema/blocks.py
docxblocks/schema/shared.py
docxblocks/utils/placeholder.py
docxblocks/utils/styles.py
docxblocks/utils/text_processing.py
docxblocks-1.6.6.dist-info/licenses/LICENSE
docxblocks-1.6.6.dist-info/METADATA
docxblocks-1.6.6.dist-info/WHEEL
docxblocks-1.6.6.dist-info/top_level.txt
docxblocks-1.6.6.dist-info/RECORD
