Metadata-Version: 2.4
Name: docxblocks
Version: 1.6.6
Summary: Block-based Word document builder with simple, predictable newline and inline text handling.
Author-email: Frank Snelling <frank.snelling03@gmail.com>
License-Expression: MIT
Project-URL: Homepage, https://github.com/frank-895/docxblocks
Project-URL: Repository, https://github.com/frank-895/docxblocks
Keywords: docx,python-docx,word,reporting,template,automation
License-File: LICENSE
Requires-Dist: python-docx>=0.8.11
Requires-Dist: Pillow>=10.0.0
Requires-Dist: pydantic>=2.0.0
Dynamic: license-file
